pycpidr/__init__.py
pycpidr-0.3.2.dist-info/METADATA
pycpidr-0.3.2.dist-info/WHEEL
pycpidr-0.3.2.dist-info/RECORD
