Metadata-Version: 2.1
Name: pycpidr
Version: 0.3.2
Summary: DEPRECATED: Python library for computing propositional idea density (Use ideadensity package instead). Requires Python 3.10-3.12.
Home-page: https://github.com/jrrobison1/pycpidr
License: GNU GPLv2
Keywords: nlp,idea density,linguistics,deprecated
Author: Jason Robison
Author-email: jrrobison@protonmail.com
Requires-Python: >=3.10,<3.13
Classifier: Development Status :: 7 - Inactive
Classifier: Intended Audience :: Developers
Classifier: License :: OSI Approved :: GNU General Public License v2 (GPLv2)
Classifier: License :: Other/Proprietary License
Classifier: Programming Language :: Python :: 3
Classifier: Programming Language :: Python :: 3.10
Classifier: Programming Language :: Python :: 3.11
Classifier: Programming Language :: Python :: 3.12
Requires-Dist: ideadensity (>=0.2.0)
Project-URL: Repository, https://github.com/jrrobison1/pycpidr
